LICENSE
MANIFEST.in
README.md
setup.py
jelm/__init__.py
jelm/_version.py
jelm.egg-info/PKG-INFO
jelm.egg-info/SOURCES.txt
jelm.egg-info/dependency_links.txt
jelm.egg-info/top_level.txt
jelm/core/__init__.py
jelm/core/edge_class.py
jelm/core/io.py
jelm/core/jelm_class.py
jelm/core/node_class.py
jelm/tests/__init__.py
jelm/tests/network_case_set_class.py
jelm/tests/network_cases.py
jelm/tests/test_io.py
jelm/tests/test_jelm_class.py
jelm/tests/test_node_class.py