Metadata-Version: 2.1
Name: jelm
Version: 0.1.0
Summary: python graph description
Home-page: https://github.com/endremborza/jelm
Author: Endre Márk Borza
Author-email: endremborza@gmail.com
License: MIT
Keywords: network graph json edgelist framework
Platform: UNKNOWN
Classifier: License :: OSI Approved :: MIT License
Requires-Python: >=3.6
